Metadata-Version: 1.0
Name: aispeech-logger
Version: 0.11.6
Summary: test for balogger
Home-page: http://www.unasm.com
Author: jiamin.dou
Author-email: jiamin.dou@aispeech.com
License: MIT License
Keywords: aispeech
Platform: any
